fiddy/__init__.py
fiddy/constants.py
fiddy/difference.py
fiddy/function.py
fiddy/gradient_check.py
fiddy/misc.py
fiddy/quotient.py
fiddy/step.py
fiddy/version.py
fiddy/extensions/__init__.py
fiddy/extensions/amici/__init__.py
fiddy/extensions/amici/amici.py
fiddy-0.0.1.dist-info/LICENSE
fiddy-0.0.1.dist-info/METADATA
fiddy-0.0.1.dist-info/WHEEL
fiddy-0.0.1.dist-info/top_level.txt
fiddy-0.0.1.dist-info/RECORD
